bc_korea_vector_map/__init__.py
bc_korea_vector_map-0.2.1.dist-info/LICENSE
bc_korea_vector_map-0.2.1.dist-info/METADATA
bc_korea_vector_map-0.2.1.dist-info/WHEEL
bc_korea_vector_map-0.2.1.dist-info/top_level.txt
bc_korea_vector_map-0.2.1.dist-info/RECORD
