Metadata-Version: 2.1
Name: bc-korea-vector-map
Version: 0.2.1
Summary: 한국 백터 지도
Author-email: WooYoung Moon <wymoon@gmail.com>
Classifier: Programming Language :: Python :: 2
Classifier: License :: OSI Approved :: MIT License
Requires-Python: >=2.3
License-File: LICENSE
